{
    "swagger": "2.0",
    "info": {
        "description": "This is a config for Amethis API.",
        "title": "Amethis API",
        "termsOfService": "http://swagger.io/terms/",
        "contact": {
            "name": "API Support",
            "email": "fiber@swagger.io"
        },
        "license": {
            "name": "Apache 2.0",
            "url": "http://www.apache.org/licenses/LICENSE-2.0.html"
        },
        "version": "1.0"
    },
    "basePath": "/v1",
    "paths": {
        "/health": {
            "get": {
                "description": "Health Check for the API",
                "consumes": [
                    "application/json"
                ],
                "produces": [
                    "application/json"
                ],
                "tags": [
                    "Health Check"
                ],
                "summary": "Health Check API",
                "responses": {
                    "200": {
                        "description": "OK",
                        "schema": {
                            "type": "object",
                            "additionalProperties": true
                        }
                    }
                }
            }
        }
    }
}